{
  "tool_name": "Bash",
  "tool_input_preview": "{\"command\":\"git diff --stat HEAD .codex/config.toml .omc/state/hud-stdin-cache.json .omc/state/last-tool-error.json .pi/settings.json package.json pnpm-lock.yaml src/pages/inventory/ProductDetailPage....",
  "error": "Exit code 128\nfatal: .omc/state/agent-replay-fa0d969b-d933-4637-a9b6-19d0d2ab98ca.jsonl: no such path in the working tree.\nUse 'git <command> -- <path>...' to specify paths that do not exist locally.",
  "timestamp": "2026-04-19T03:01:53.965Z",
  "retry_count": 4
}